chariot_base/__init__.py
chariot_base/connector/__init__.py
chariot_base/connector/local.py
chariot_base/connector/watson.py
chariot_base/datasource/__init__.py
chariot_base/datasource/cloud.py
chariot_base/datasource/local.py
chariot_base/middleware/__init__.py
chariot_base/middleware/tracing.py
chariot_base/model/__init__.py
chariot_base/model/alert.py
chariot_base/model/message.py
chariot_base/model/point.py
chariot_base/model/subscriber.py
chariot_base/tests/__init__.py
chariot_base/tests/utils.py
chariot_base/utilities/__init__.py
chariot_base/utilities/configuration.py
chariot_base/utilities/encryption.py
chariot_base/utilities/health.py
chariot_base/utilities/iotlwrap.py
chariot_base/utilities/parsing.py
chariot_base/utilities/permission.py
chariot_base/utilities/topology.py
chariot_base/utilities/tracing.py
chariot_base-0.16.0.dist-info/AUTHORS.rst
chariot_base-0.16.0.dist-info/LICENSE
chariot_base-0.16.0.dist-info/METADATA
chariot_base-0.16.0.dist-info/WHEEL
chariot_base-0.16.0.dist-info/top_level.txt
chariot_base-0.16.0.dist-info/RECORD
