Metadata-Version: 2.1
Name: chariot-base
Version: 0.16.0
Summary: Chariot base micro-service
Home-page: https://gitlab.com/chariot-h2020/chariot_base
Author: George Theofilis
Author-email: g.theofilis@clmsuk.com
License: EPL-1.0
Keywords: chariot_base
Platform: UNKNOWN
Classifier: License :: OSI Approved :: Eclipse Public License 1.0 (EPL-1.0)
Classifier: Programming Language :: Python
Classifier: Programming Language :: Python :: 3
Classifier: Programming Language :: Python :: 3.6
Classifier: Programming Language :: Python :: Implementation :: CPython
Classifier: Programming Language :: Python :: Implementation :: PyPy
Requires-Dist: paho-mqtt
Requires-Dist: asyncio
Requires-Dist: gmqtt
Requires-Dist: influxdb
Requires-Dist: cloudant
Requires-Dist: wiotp-sdk
Requires-Dist: pytest
Requires-Dist: fastecdsa
Requires-Dist: ecdsa
Requires-Dist: pycrypto
Requires-Dist: jaeger-client
Requires-Dist: pytest-asyncio
Requires-Dist: falcon
